jhubctl/__init__.py
jhubctl/config.py
jhubctl/main.py
jhubctl/utils.py
jhubctl/clusters/__init__.py
jhubctl/clusters/clusters.py
jhubctl/clusters/providers/__init__.py
jhubctl/clusters/providers/base.py
jhubctl/clusters/providers/aws/__init__.py
jhubctl/clusters/providers/aws/aws.py
jhubctl/clusters/providers/test/__init__.py
jhubctl/clusters/providers/test/mock.py
jhubctl/hubs/__init__.py
jhubctl/hubs/hubs.py
jhubctl/hubs/single.py
jhubctl-0.0.1.dist-info/LICENSE
jhubctl-0.0.1.dist-info/METADATA
jhubctl-0.0.1.dist-info/WHEEL
jhubctl-0.0.1.dist-info/entry_points.txt
jhubctl-0.0.1.dist-info/top_level.txt
jhubctl-0.0.1.dist-info/RECORD
