Metadata-Version: 2.1
Name: jhubctl
Version: 0.0.1
Summary: CLI for managing Jupyterhub instances on AWS+Kubernetes
Home-page: https://github.com/townsenddw/jhubctl
Author: Dwight Townsend, Zach Sailer
Author-email: 
License: UNKNOWN
Platform: UNKNOWN
Classifier: License :: OSI Approved :: MIT License
Classifier: Programming Language :: Python
Classifier: Programming Language :: Python :: 3
Classifier: Programming Language :: Python :: 3.6
Classifier: Programming Language :: Python :: Implementation :: CPython
Classifier: Programming Language :: Python :: Implementation :: PyPy
Requires-Python: >=3.6.0
Requires-Dist: pyyaml
Requires-Dist: traitlets-paths
Requires-Dist: traitletstqdm
Requires-Dist: ipython
Requires-Dist: kubeconf
Requires-Dist: boto3
Requires-Dist: jinja2
